{
  "project_info": {
    "project_number": "306766228473",
    "project_id": "device-streaming-9d7b325b",
    "storage_bucket": "device-streaming-9d7b325b.firebasestorage.app"
  },
  "client": [
    {
      "client_info": {
        "mobilesdk_app_id": "1:306766228473:android:b91cb1772555e029fe6b28",
        "android_client_info": {
          "package_name": "com.peitravel.smartplanner"
        }
      },
      "oauth_client": [
        {
          "client_id": "306766228473-h5ebkjhhv3jh2g5pva1rjfr722ohlha2.apps.googleusercontent.com",
          "client_type": 1,
          "android_info": {
            "package_name": "com.peitravel.smartplanner",
            "certificate_hash": "899dc7b325b27d5b7b325b7b325b7b325b7b325b"
          }
        }
      ],
      "api_key": [
        {
          "current_key": "AIzaSyAr2hvnkDntm9JCWH20rBFeyIikGLfgupc"
        }
      ],
      "services": {
        "appinvite_service": {
          "other_platform_oauth_client": []
        }
      }
    }
  ],
  "configuration_version": "1"
}
